<?xml version="1.0" encoding="UTF-8" ?>
<Data>
  <Series>
    <id>176941</id>
    <Actors>|Martin Freeman|Benedict Cumberbatch|Mark Gatiss|Una Stubbs|Rupert Graves|Louise Brealey|Lara Pulver|Andrew Scott|</Actors>
    <Airs_DayOfWeek>Sunday</Airs_DayOfWeek>
    <Airs_Time>8:30 PM</Airs_Time>
    <ContentRating>TV-14</ContentRating>
    <FirstAired>2010-07-25</FirstAired>
    <Genre>|Action and Adventure|Drama|</Genre>
    <IMDB_ID>tt1475582</IMDB_ID>
    <Language>en</Language>
    <Network>BBC One</Network>
    <NetworkID></NetworkID>
    <Overview>Sherlock depicts &quot;consulting detective&quot; Holmes, assisting the Metropolitan Police Service, primarily DI Greg Lestrade, in solving various crimes. Holmes is assisted by his flatmate, Dr John Watson, who has returned from military service in Afghanistan. Although the series depicts a variety of crimes and perpetrators, Holmes' conflict with his archnemesis Jim Moriarty is a recurring feature.</Overview>
    <Rating>9.3</Rating>
    <RatingCount>170</RatingCount>
    <Runtime>90</Runtime>
    <SeriesID>79744</SeriesID>
    <SeriesName>Sherlock</SeriesName>
    <Status>Continuing</Status>
    <added>2010-07-20 01:40:01</added>
    <addedBy>63541</addedBy>
    <banner>graphical/176941-g.jpg</banner>
    <fanart>fanart/original/176941-3.jpg</fanart>
    <lastupdated>1357507139</lastupdated>
    <poster>posters/176941-4.jpg</poster>
    <zap2it_id>SH01304269</zap2it_id>
  </Series>
</Data>
