<?xml version="1.0" encoding="UTF-8" ?>
<Data>
  <Series>
    <id>250487</id>
    <Actors>|Dylan McDermott|Connie Britton|Jessica Lange|Alex Breckenridge|Frances Conroy|Zachary Quinto|Evan Peters|Denis O'Hare|Taissa Farmiga|</Actors>
    <Airs_DayOfWeek>Wednesday</Airs_DayOfWeek>
    <Airs_Time>10:00 PM</Airs_Time>
    <ContentRating>TV-MA</ContentRating>
    <FirstAired>2011-10-05</FirstAired>
    <Genre>|Drama|Fantasy|</Genre>
    <IMDB_ID>tt1844624</IMDB_ID>
    <Language>en</Language>
    <Network>FX</Network>
    <NetworkID></NetworkID>
    <Overview>The series centers on the Harmon family: Ben, Vivien and their daughter Violet, who move from Boston to Los Angeles after Vivien has a miscarriage and Ben has an affair. They move into a restored mansion, unaware that the home is haunted by its former inhabitants.</Overview>
    <Rating>8.2</Rating>
    <RatingCount>48</RatingCount>
    <Runtime>60</Runtime>
    <SeriesID>81011</SeriesID>
    <SeriesName>American Horror Story</SeriesName>
    <Status>Continuing</Status>
    <added>2011-07-26 07:19:34</added>
    <addedBy>346503</addedBy>
    <banner>graphical/250487-g.jpg</banner>
    <fanart>fanart/original/250487-7.jpg</fanart>
    <lastupdated>1349089042</lastupdated>
    <poster>posters/250487-11.jpg</poster>
    <zap2it_id>SH01466178</zap2it_id>
  </Series>
</Data>
